maroon/__init__.py
maroon/cli.py
maroon/cue.py
maroon/rename.py
maroon/transform.py
maroon-0.2.0.dist-info/LICENSE
maroon-0.2.0.dist-info/METADATA
maroon-0.2.0.dist-info/WHEEL
maroon-0.2.0.dist-info/entry_points.txt
maroon-0.2.0.dist-info/RECORD
